README.md
setup.cfg
setup.py
scripts/send-cli
sendclient/common.py
sendclient/delete.py
sendclient/download.py
sendclient/params.py
sendclient/password.py
sendclient/upload.py
sendclient.egg-info/PKG-INFO
sendclient.egg-info/SOURCES.txt
sendclient.egg-info/dependency_links.txt
sendclient.egg-info/requires.txt
sendclient.egg-info/top_level.txt