Metadata-Version: 1.1
Name: sendclient
Version: 0.2.0
Summary: Unofficial Firefox Send client
Home-page: https://github.com/ehuggett/send-cli
Author: Edmund Huggett
Author-email: edmund.huggett@fsfe.org
License: GNU General Public License v3 or later (GPLv3+)
Platform: UNKNOWN
Classifier: Topic :: Communications :: File Sharing
Classifier: Development Status :: 3 - Alpha
Classifier: Environment :: Console
Classifier: License :: OSI Approved :: GNU General Public License v3 or later (GPLv3+)
Classifier: Programming Language :: Python :: 3
Classifier: Programming Language :: Python :: 3.2
Classifier: Programming Language :: Python :: 3.3
Classifier: Programming Language :: Python :: 3.4
Classifier: Programming Language :: Python :: 3.5
Classifier: Programming Language :: Python :: 3.6
